django_geo_spaas-3.0.0.dev4.dist-info/licenses/LICENSE
geospaas/__init__.py
geospaas/admin.py
geospaas/models.py
geospaas/tests.py
geospaas/urls.py
geospaas/base_viewer/README.md
geospaas/base_viewer/__init__.py
geospaas/base_viewer/apps.py
geospaas/base_viewer/forms.py
geospaas/base_viewer/tests.py
geospaas/base_viewer/urls.py
geospaas/base_viewer/views.py
geospaas/base_viewer/static/base_viewer/styles.css
geospaas/base_viewer/static/base_viewer/js/base_viewer.js
geospaas/base_viewer/static/base_viewer/js/leaflet.ajax.min.js
geospaas/base_viewer/templates/base_viewer/ds_info.html
geospaas/base_viewer/templates/base_viewer/elements.html
geospaas/base_viewer/templates/base_viewer/page_structure.html
geospaas/catalog/README.md
geospaas/catalog/__init__.py
geospaas/catalog/admin.py
geospaas/catalog/models.py
geospaas/catalog/tests.py
geospaas/catalog/views.py
geospaas/catalog/fixtures/catalog.json
geospaas/catalog/management/__init__.py
geospaas/catalog/management/commands/__init__.py
geospaas/catalog/management/commands/count.py
geospaas/catalog/migrations/0001_initial.py
geospaas/catalog/migrations/0002_auto_20160705_1331.py
geospaas/catalog/migrations/0003_dataset_entry_id.py
geospaas/catalog/migrations/0004_populate_entry_id_values.py
geospaas/catalog/migrations/0005_remove_entry_id_null.py
geospaas/catalog/migrations/0006_auto_20190130_1442.py
geospaas/catalog/migrations/0007_auto_20190626_1313.py
geospaas/catalog/migrations/0008_auto_20200331_0806.py
geospaas/catalog/migrations/0009_auto_20201012_0905.py
geospaas/catalog/migrations/0010_auto_20201019_1331.py
geospaas/catalog/migrations/0011_auto_20210525_1252.py
geospaas/catalog/migrations/0012_auto_20250512_1411.py
geospaas/catalog/migrations/0013_auto_20250512_1414.py
geospaas/catalog/migrations/0014_auto_20250513_1302.py
geospaas/catalog/migrations/0015_auto_20250515_1401.py
geospaas/catalog/migrations/0016_auto_20250625_0644.py
geospaas/catalog/migrations/__init__.py
geospaas/utils/__init__.py
geospaas/utils/processing_base_command.py
geospaas/utils/utils.py
django_geo_spaas-3.0.0.dev4.dist-info/METADATA
django_geo_spaas-3.0.0.dev4.dist-info/WHEEL
django_geo_spaas-3.0.0.dev4.dist-info/top_level.txt
django_geo_spaas-3.0.0.dev4.dist-info/RECORD
