Metadata-Version: 2.4
Name: django-geo-spaas
Version: 3.0.0.dev4
Summary: Tools to manage geospatial datasets
Author: Morten W. Hansen, Artem Moiseev, Jeong-Won Park, Adrien Perrin, Arash Azamifard
Author-email: "Anton A. Korosov" <anton.korosov@nersc.no>
License:                     GNU GENERAL PUBLIC LICENSE
Project-URL: Repository, https://github.com/nansencenter/django-geo-spaas
Classifier: Development Status :: 4 - Beta
Classifier: Environment :: Web Environment
Classifier: Framework :: Django
Classifier: Intended Audience :: Developers
Classifier: License :: OSI Approved :: GNU General Public License v3 (GPLv3)
Classifier: Operating System :: OS Independent
Classifier: Programming Language :: Python
Classifier: Topic :: Utilities
License-File: LICENSE
Requires-Dist: django-forms-bootstrap
Requires-Dist: django-leaflet
Requires-Dist: django<4
Requires-Dist: gdal
Requires-Dist: nansat
Requires-Dist: netCDF4
Requires-Dist: pythesint==1.7.3.dev0
Dynamic: license-file
